gilgamesh_summarizer/KnowledgeGraph.py
gilgamesh_summarizer/Rewriter.py
gilgamesh_summarizer/SparqlRewriter.py
gilgamesh_summarizer/Summarizer.py
gilgamesh_summarizer/__init__.py
gilgamesh_summarizer/kvpair.py
gilgamesh_summarizer/utils.py
gilgamesh_summarizer-0.2.7.dist-info/LICENSE
gilgamesh_summarizer-0.2.7.dist-info/METADATA
gilgamesh_summarizer-0.2.7.dist-info/WHEEL
gilgamesh_summarizer-0.2.7.dist-info/top_level.txt
gilgamesh_summarizer-0.2.7.dist-info/RECORD
