Metadata-Version: 2.1
Name: gilgamesh-summarizer
Version: 0.2.7
Summary: A package for summarizing RDF graphs for Question Answering pipelines
Home-page: UNKNOWN
Author: Kostas Plas
Author-email: kplas@di.uoa.gr
License: UNKNOWN
Platform: UNKNOWN
Classifier: Programming Language :: Python :: 3
Classifier: License :: OSI Approved :: MIT License
Requires-Python: >=3.10
License-File: LICENSE
Requires-Dist: networkx
Requires-Dist: pandas
Requires-Dist: pyjedai
Requires-Dist: rdflib
Requires-Dist: torch
Requires-Dist: tqdm
Requires-Dist: transformers
Requires-Dist: unsloth
